README.rst
setup.py
partialhash/__init__.py
partialhash/version.py
partialhash.egg-info/PKG-INFO
partialhash.egg-info/SOURCES.txt
partialhash.egg-info/dependency_links.txt
partialhash.egg-info/not-zip-safe
partialhash.egg-info/top_level.txt
tests/__init__.py
tests/correctness.py
tests/errors.py
tests/profile.py