Metadata-Version: 1.1
Name: partialhash
Version: 1.1.3
Summary: Library to partialy hash files.
Home-page: https://github.com/F483/partialhash/
Author: Fabian Barkhau
Author-email: fabian.barkhau@gmail.com
License: MIT
Download-URL: https://pypi.python.org/packages/source/a/partialhash/partialhash-1.1.3.tar.gz
Keywords: sha256,partial,hash
Platform: UNKNOWN
Classifier: Development Status :: 5 - Production/Stable
Classifier: Intended Audience :: Developers
Classifier: License :: OSI Approved :: MIT License
Classifier: Operating System :: OS Independent
Classifier: Programming Language :: Python
Classifier: Programming Language :: Python :: 2
Classifier: Programming Language :: Python :: 2.7
Classifier: Programming Language :: Python :: 3
Classifier: Programming Language :: Python :: 3.3
Classifier: Programming Language :: Python :: 3.4
Classifier: Topic :: Software Development :: Libraries :: Python Modules
